odoo8_addon_hr_recruitment_partner-8.0.1.0.0.99.dev43-py3.8-nspkg.pth
odoo_addons/hr_recruitment_partner/README.rst
odoo_addons/hr_recruitment_partner/__init__.py
odoo_addons/hr_recruitment_partner/__openerp__.py
odoo_addons/hr_recruitment_partner/init_hooks.py
odoo_addons/hr_recruitment_partner/i18n/ar.po
odoo_addons/hr_recruitment_partner/i18n/bg.po
odoo_addons/hr_recruitment_partner/i18n/bs.po
odoo_addons/hr_recruitment_partner/i18n/ca.po
odoo_addons/hr_recruitment_partner/i18n/ca_ES.po
odoo_addons/hr_recruitment_partner/i18n/cs.po
odoo_addons/hr_recruitment_partner/i18n/da.po
odoo_addons/hr_recruitment_partner/i18n/da_DK.po
odoo_addons/hr_recruitment_partner/i18n/de.po
odoo_addons/hr_recruitment_partner/i18n/el_GR.po
odoo_addons/hr_recruitment_partner/i18n/en_GB.po
odoo_addons/hr_recruitment_partner/i18n/es.po
odoo_addons/hr_recruitment_partner/i18n/es_AR.po
odoo_addons/hr_recruitment_partner/i18n/es_CL.po
odoo_addons/hr_recruitment_partner/i18n/es_CO.po
odoo_addons/hr_recruitment_partner/i18n/es_CR.po
odoo_addons/hr_recruitment_partner/i18n/es_DO.po
odoo_addons/hr_recruitment_partner/i18n/es_EC.po
odoo_addons/hr_recruitment_partner/i18n/es_ES.po
odoo_addons/hr_recruitment_partner/i18n/es_MX.po
odoo_addons/hr_recruitment_partner/i18n/es_PE.po
odoo_addons/hr_recruitment_partner/i18n/es_PY.po
odoo_addons/hr_recruitment_partner/i18n/es_VE.po
odoo_addons/hr_recruitment_partner/i18n/et.po
odoo_addons/hr_recruitment_partner/i18n/fa.po
odoo_addons/hr_recruitment_partner/i18n/fi.po
odoo_addons/hr_recruitment_partner/i18n/fr.po
odoo_addons/hr_recruitment_partner/i18n/fr_CA.po
odoo_addons/hr_recruitment_partner/i18n/fr_CH.po
odoo_addons/hr_recruitment_partner/i18n/fr_FR.po
odoo_addons/hr_recruitment_partner/i18n/gl.po
odoo_addons/hr_recruitment_partner/i18n/he.po
odoo_addons/hr_recruitment_partner/i18n/hr.po
odoo_addons/hr_recruitment_partner/i18n/hr_HR.po
odoo_addons/hr_recruitment_partner/i18n/hr_recruitment_partner.pot
odoo_addons/hr_recruitment_partner/i18n/hu.po
odoo8_addon_hr_recruitment_partner-8.0.1.0.0.99.dev43.dist-info/METADATA
odoo8_addon_hr_recruitment_partner-8.0.1.0.0.99.dev43.dist-info/WHEEL
odoo8_addon_hr_recruitment_partner-8.0.1.0.0.99.dev43.dist-info/namespace_packages.txt
odoo8_addon_hr_recruitment_partner-8.0.1.0.0.99.dev43.dist-info/top_level.txt
odoo8_addon_hr_recruitment_partner-8.0.1.0.0.99.dev43.dist-info/RECORD
